setup.py
src/digimat/__init__.py
src/digimat.nestcam.egg-info/PKG-INFO
src/digimat.nestcam.egg-info/SOURCES.txt
src/digimat.nestcam.egg-info/dependency_links.txt
src/digimat.nestcam.egg-info/namespace_packages.txt
src/digimat.nestcam.egg-info/not-zip-safe
src/digimat.nestcam.egg-info/requires.txt
src/digimat.nestcam.egg-info/top_level.txt
src/digimat/nestcam/__init__.py
src/digimat/nestcam/nestcam.py