Metadata-Version: 1.0
Name: digimat.nestcam
Version: 0.1.4
Summary: Digimat Nestcam
Home-page: UNKNOWN
Author: Frederic Hess
Author-email: fhess@splust.ch
License: PSF
Platform: UNKNOWN
